k8smith/__init__.py
k8smith/py.typed
k8smith/aws/__init__.py
k8smith/azure/__init__.py
k8smith/core/__init__.py
k8smith/core/builder.py
k8smith/core/configmap.py
k8smith/core/cronjob.py
k8smith/core/daemonset.py
k8smith/core/deployment.py
k8smith/core/hpa.py
k8smith/core/ingress.py
k8smith/core/models.py
k8smith/core/namespace.py
k8smith/core/pdb.py
k8smith/core/rbac.py
k8smith/core/secret.py
k8smith/core/service.py
k8smith/core/serviceaccount.py
k8smith/core/statefulset.py
k8smith/gke/__init__.py
k8smith/gke/backendpolicy.py
k8smith/gke/gateway.py
k8smith/gke/healthcheck.py
k8smith/gke/httproute.py
k8smith/gke/models.py
k8smith/gke/monitoring.py
k8smith/output/__init__.py
k8smith/output/manifest.py
k8smith/output/yaml.py
k8smith/validation/__init__.py
k8smith/validation/core.py
k8smith/validation/validators.py
k8smith-0.4.1.dist-info/METADATA
k8smith-0.4.1.dist-info/WHEEL
k8smith-0.4.1.dist-info/licenses/LICENSE
k8smith-0.4.1.dist-info/RECORD
