Metadata-Version: 2.4
Name: k8smith
Version: 0.4.1
Summary: A transparent, lightweight Kubernetes manifest generator
Project-URL: Homepage, https://github.com/eliminyro/k8smith
Project-URL: Documentation, https://eliminyro.github.io/k8smith
Project-URL: Repository, https://github.com/eliminyro/k8smith
Author: Pavel Eliminyro (eliminyro)
License: GPL-3.0-only
License-File: LICENSE
Keywords: devops,k8s,kubernetes,manifest,yaml
Classifier: Development Status :: 3 - Alpha
Classifier: Intended Audience :: Developers
Classifier: License :: OSI Approved :: GNU General Public License v3 (GPLv3)
Classifier: Programming Language :: Python :: 3
Classifier: Programming Language :: Python :: 3.11
Classifier: Programming Language :: Python :: 3.12
Classifier: Programming Language :: Python :: 3.13
Classifier: Programming Language :: Python :: 3.14
Classifier: Topic :: Software Development :: Code Generators
Classifier: Topic :: System :: Systems Administration
Requires-Python: >=3.11
Requires-Dist: pydantic>=2.0
Requires-Dist: pyyaml>=6.0
Provides-Extra: dev
Requires-Dist: mypy>=1.10; extra == 'dev'
Requires-Dist: pytest-snapshot>=0.9; extra == 'dev'
Requires-Dist: pytest>=8.0; extra == 'dev'
Requires-Dist: ruff>=0.4; extra == 'dev'
Requires-Dist: types-pyyaml>=6.0; extra == 'dev'
Provides-Extra: docs
Requires-Dist: mkdocs-material>=9.5; extra == 'docs'
Requires-Dist: mkdocs>=1.6; extra == 'docs'
Requires-Dist: mkdocstrings[python]>=0.24; extra == 'docs'
